FPGA-Assgn2/module2.v
module module2();

    reg [31:0] val[39:0];
    reg [4:0] i1 [39:0];
    reg [4:0] i2 [39:0];
    reg cp [39:0];
initial begin
    val[0] =14; 
i1 [0]=4;
i2[0]=18;
cp[0]=1;
val[1] =89; 
i1[1]=9;
i2[1]=9;
    cp[1]=1;
val[2] =48; 
i1[2]=12;
i2[2]=8;
    cp[2]=1;
val[3] =76; 
i1[3]=16;
i2[3]=16;
    cp[3]=1;
val[4] =13; 
i1[4]=17;
i2[4]=5;
    cp[4]=1;
val[5]=82; 
i1[5]=8;
i2[5]=2;
    cp[5]=1;
val[6]=70; 
i1[6]=0;
i2[6]=10;
    cp[6]=1;
val[7]=11; 
i1[7]=11;
i2[7]=19;
    cp[7]=1;
val[8]=91; 
i1[8]=11;
i2[8]=11;
    cp[8]=1;
val[9] =13; 
i1[9]=17;
i2[9]=5;
    cp[9]=1;

end


    
    
endmodule

FPGA-Assgn2/module1.v
module mod1();
// output  reg [31:0] table1 [19:0],
// output reg table1_filled [19:0],
// output reg [31:0] table2 [19:0],
// output reg table2_filled [19:0]

// );


reg [31:0] table1 [19:0];
reg table1_filled [19:0];
reg [31:0] table2 [19:0];
reg table2_filled [19:0];


integer i;


initial begin
    for (i=0 ; i<20 ; i++) begin
    table1_filled [i]= 1'b0 ;
    table2_filled [i]= 1'b0 ;
end;

table1 [4] = 14 ;  table1_filled [4]=1;
table1 [9] = 89;  table1_filled [9]=1;
table1 [12]=48 ;  table1_filled [12]=1;
table1 [16]=76;  table1_filled [16]=1;
table1 [17]=13;  table1_filled [17]=1;

    table2 [2] = 82 ;  table2_filled [2]=1;
    table2 [10] = 70 ;  table2_filled [10]=1;
    table2 [19]=11 ;  table2_filled [19]=1;
    table2 [11]=91 ;  table2_filled [11]=1;
table2 [5]=13;  table2_filled [5]=1;

    for (i=0 ; i<20 ;i++) begin
        $display("%d : %d %d", i , table1_filled[i] , table1[i]);

    end;
     for (i=0 ; i<20 ;i++) begin
        $display("%d : %d %d", i , table2_filled[i] , table2[i]);

    end;
    
end


    
endmodule

FPGA-Assgn2/module3.v
`include "module1.v"
`include "module2.v"
`timescale 1ns/1ns
//val, i1, i2

module mod3(input [31:0] num,
            input [4:0] index1,
            input [4:0] index2,
            input clk,
            input reset
            );

        wire status;
        reg stat;
        reg [4:0] curr_index;
        
        //reg [4:0] next_index;
        reg [31:0] curr;
        reg [31:0] in_num;
        integer k =0;

        mod1 m1();
        module2 m2();
        
        assign status = stat & clk;

        initial begin
            #2;
        stat <= 1;
        curr_index <= index1;
        curr <= num;
        in_num <= num;
        end

        always @(reset) begin
            stat <= 1;
            curr_index <= index1;
        curr <= num;
        in_num <= num;
        end
          
        always @(posedge status or negedge status) begin
            
            #2;
            if(m1.table1_filled[curr_index] == 0 && status == 1) begin
                m1.table1_filled[curr_index] <= 1;
                m1.table1[curr_index] <= in_num;
                for(k = 0; k < 40 && m2.cp[k] == 1; k+=1) begin
                    
                end
                m2.cp[k] <= 1;
                m2.val[k] <= num;
                m2.i1[k] <= index1;
                m2.i2[k] <= index2; 
                stat <= 0;
            end
            else if(m1.table2_filled[curr_index] == 0 && status == 0) begin
                m1.table2_filled[curr_index] <= 1;
                m1.table2[curr_index] <= in_num;
                for(k = 0; k < 40 && m2.cp[k] == 1; k+=1) begin
                    
                end
                m2.cp[k] <= 1;
                m2.val[k] <= num;
                m2.i1[k] <= index1;
                m2.i2[k] <= index2; 
                stat <= 0;
            end
            else if(status == 1) begin
                for(integer j = 0; j<40 && m2.cp[j] == 1; j+=1) begin
                    if(m2.i1[j] == curr_index) begin
                        curr <= m2.val[j];
                        curr_index <= m2.i2[j];
                        m2.val[j] <= in_num;
                        in_num <= curr;
                    end
                end
                //status <= ~status;
            end
            else begin
                for(integer j = 0; j<40 && m2.cp[j] == 1; j+=1) begin
                    if(m2.i2[j] == curr_index) begin
                        curr <= m2.val[j];
                        curr_index <= m2.i1[j];
                        m2.val[j] <= in_num;
                        in_num <= curr;
                    end
                end
                //status <= ~status;
            end

        end
    
    
endmodule

FPGA-Assgn2/testbench.v
`include "module3.v"
`timescale 1ns/1ns
module tb;

reg [31:0] num;
reg [4:0] i1,i2;
reg clk;
reg reset;

mod3 uut (.num(num)  ,  .index1(i1)  ,  .index2(i2), .clk(clk), .reset(reset));

always begin
    #1;
    clk <= ~clk;
end

initial begin
    clk <= 1;
    $dumpfile("dump.vcd");
    $dumpvars(0,tb);
    
    num <=38;  i1 <=12;   i2 <=18;
    #100;
    for (integer i=0 ; i<20 ;i++) begin
        $display("%d : %d %d", i , uut.m1.table1_filled[i] , uut.m1.table1[i]);
    end;
    $display("\n");
    for (integer i=0 ; i<20 ;i++) begin
        $display("%d : %d %d", i , uut.m1.table2_filled[i] , uut.m1.table2[i]);
    end;
    $display("\n"); 
    reset <= ~reset;
    num <=84;  i1 <=4;   i2 <=4;
    #100;
    for (integer i=0 ; i<20 ;i++) begin
        $display("%d : %d %d", i , uut.m1.table1_filled[i] , uut.m1.table1[i]);
    end;
    $display("\n");
    for (integer i=0 ; i<20 ;i++) begin
        $display("%d : %d %d", i , uut.m1.table2_filled[i] , uut.m1.table2[i]);
    end;
    $display("\n"); 
    reset <= ~reset;
    num <=76;  i1 <=16;   i2 <=16;
    #100;
    for (integer i=0 ; i<20 ;i++) begin
        $display("%d : %d %d", i , uut.m1.table1_filled[i] , uut.m1.table1[i]);
    end;
    $display("\n");
    for (integer i=0 ; i<20 ;i++) begin
        $display("%d : %d %d", i , uut.m1.table2_filled[i] , uut.m1.table2[i]);
    end;
    $display("\n"); 
    reset <= ~reset;
    num <=93;  i1 <=17;   i2 <=13;
    #100;
    for (integer i=0 ; i<20 ;i++) begin
        $display("%d : %d %d", i , uut.m1.table1_filled[i] , uut.m1.table1[i]);
    end;
    $display("\n");
    for (integer i=0 ; i<20 ;i++) begin
        $display("%d : %d %d", i , uut.m1.table2_filled[i] , uut.m1.table2[i]);
    end;
    $display("\n"); 
    reset <= ~reset;
    num <=8;  i1 <=12;   i2 <=4;
    #100;
    for (integer i=0 ; i<20 ;i++) begin
        $display("%d : %d %d", i , uut.m1.table1_filled[i] , uut.m1.table1[i]);
    end;
    $display("\n");
    for (integer i=0 ; i<20 ;i++) begin
        $display("%d : %d %d", i , uut.m1.table2_filled[i] , uut.m1.table2[i]);
    end;
    $display("\n"); 
    $finish;
end
endmodule

FPGA-Assgn2/dump.vcd
$date
	Thu Jun 09 01:24:57 2022
$end
$version
	Icarus Verilog
$end
$timescale
	1ns
$end
$scope module tb $end
$var reg 1 ! clk $end
$var reg 5 " i1 [4:0] $end
$var reg 5 # i2 [4:0] $end
$var reg 32 $ num [31:0] $end
$var reg 1 % reset $end
$scope module uut $end
$var wire 1 ! clk $end
$var wire 5 & index1 [4:0] $end
$var wire 5 ' index2 [4:0] $end
$var wire 32 ( num [31:0] $end
$var wire 1 % reset $end
$var wire 1 ) status $end
$var reg 32 * curr [31:0] $end
$var reg 5 + curr_index [4:0] $end
$var reg 32 , in_num [31:0] $end
$var reg 1 - stat $end
$var integer 32 . k [31:0] $end
$scope module m1 $end
$var integer 32 / i [31:0] $end
$upscope $end
$scope module m2 $end
$upscope $end
$scope begin $ivl_for_loop0 $end
$var integer 32 0 j [31:0] $end
$upscope $end
$scope begin $ivl_for_loop1 $end
$var integer 32 1 j [31:0] $end
$upscope $end
$upscope $end
$scope begin $ivl_for_loop2 $end
$var integer 32 2 i [31:0] $end
$upscope $end
$scope begin $ivl_for_loop3 $end
$var integer 32 3 i [31:0] $end
$upscope $end
$upscope $end
$enddefinitions $end
#0
$dumpvars
bx 3
bx 2
bx 1
bx 0
b10100 /
b0 .
x-
bx ,
bx +
bx *
x)
b100110 (
b10010 '
b1100 &
x%
b100110 $
b10010 #
b1100 "
1!
$end
#1
0)
0!
#2
1)
1!
b100110 ,
b100110 *
b1100 +
1-
#3
0)
0!
b1000 +
b110000 *
b1010 0
#4
1)
1!
#5
0)
0!
0-
b1010 .
#6
1!
#7
0!
b1011 .
#8
1!
#9
0!
#10
1!
#11
0!
#12
1!
#13
0!
#14
1!
#15
0!
#16
1!
#17
0!
#18
1!
#19
0!
#20
1!
#21
0!
#22
1!
#23
0!
#24
1!
#25
0!
#26
1!
#27
0!
#28
1!
#29
0!
#30
1!
#31
0!
#32
1!
#33
0!
#34
1!
#35
0!
#36
1!
#37
0!
#38
1!
#39
0!
#40
1!
#41
0!
#42
1!
#43
0!
#44
1!
#45
0!
#46
1!
#47
0!
#48
1!
#49
0!
#50
1!
#51
0!
#52
1!
#53
0!
#54
1!
#55
0!
#56
1!
#57
0!
#58
1!
#59
0!
#60
1!
#61
0!
#62
1!
#63
0!
#64
1!
#65
0!
#66
1!
#67
0!
#68
1!
#69
0!
#70
1!
#71
0!
#72
1!
#73
0!
#74
1!
#75
0!
#76
1!
#77
0!
#78
1!
#79
0!
#80
1!
#81
0!
#82
1!
#83
0!
#84
1!
#85
0!
#86
1!
#87
0!
#88
1!
#89
0!
#90
1!
#91
0!
#92
1!
#93
0!
#94
1!
#95
0!
#96
1!
#97
0!
#98
1!
#99
0!
#100
1!
b10100 3
b10100 2
