FPGA-Assgn2/module2.v
module module2();

    reg [31:0] val[39:0];
    reg [4:0] i1 [39:0];
    reg [4:0] i2 [39:0];
    reg cp [39:0];
initial begin
    val[0] =14; 
i1 [0]=4;
i2[0]=18;
cp[0]=1;
val[1] =89; 
i1[1]=9;
i2[1]=9;
    cp[1]=1;
val[2] =48; 
i1[2]=12;
i2[2]=8;
    cp[2]=1;
val[3] =76; 
i1[3]=16;
i2[3]=16;
    cp[3]=1;
val[4] =13; 
i1[4]=17;
i2[4]=5;
    cp[4]=1;
val[5]=82; 
i1[5]=8;
i2[5]=2;
    cp[5]=1;
val[6]=70; 
i1[6]=0;
i2[6]=10;
    cp[6]=1;
val[7]=11; 
i1[7]=11;
i2[7]=19;
    cp[7]=1;
val[8]=91; 
i1[8]=11;
i2[8]=11;
    cp[8]=1;
val[9] =13; 
i1[9]=17;
i2[9]=5;
    cp[9]=1;

end


    
    
endmodule

FPGA-Assgn2/module1.v
module mod1();
// output  reg [31:0] table1 [19:0],
// output reg table1_filled [19:0],
// output reg [31:0] table2 [19:0],
// output reg table2_filled [19:0]

// );


reg [31:0] table1 [19:0];
reg table1_filled [19:0];
reg [31:0] table2 [19:0];
reg table2_filled [19:0];


integer i;


initial begin
    for (i=0 ; i<20 ; i++) begin
    table1_filled [i]= 1'b0 ;
    table2_filled [i]= 1'b0 ;
end;

table1 [4] = 14 ;  table1_filled [4]=1;
table1 [9] = 89;  table1_filled [9]=1;
table1 [12]=48 ;  table1_filled [12]=1;
table1 [16]=76;  table1_filled [16]=1;
table1 [17]=13;  table1_filled [17]=1;

    table2 [2] = 82 ;  table2_filled [2]=1;
    table2 [10] = 70 ;  table2_filled [10]=1;
    table2 [19]=11 ;  table2_filled [19]=1;
    table2 [11]=91 ;  table2_filled [11]=1;
table2 [5]=13;  table2_filled [5]=1;

    for (i=0 ; i<20 ;i++) begin
        $display("%d : %d %d", i , table1_filled[i] , table1[i]);

    end;
     for (i=0 ; i<20 ;i++) begin
        $display("%d : %d %d", i , table2_filled[i] , table2[i]);

    end;
    
end


    
endmodule

FPGA-Assgn2/module32.v
//`include "module1.v"
//`include "module2.v"
`timescale 1ns/1ns

module mod32(input [31:0] num,
            input rin,
            output reg [31:0] num_o,
            output reg rout);

    mod1 m1();
    module2 m2();

    reg [4:0] index2;
    //reg [4:0] index2;

    always@(rin) begin
        #1;
        if (rin == 0)begin
            rout <= 0;
        end
        else begin
            for(integer i = 0; i <15; i+=1) begin
                if(m2.val[i] == num) begin
                    index2 <= m2.i2[i];
                    //index2 <= m2.i2[i];
                end
            end

            if(m1.table2_filled[index2] == 1) begin
                num_o <= m1.table2[index2];
                m1.table2[index2] <= num;
                rout <= 1;
            end
            else begin
                m1.table2_filled[index2] <= 1;
                m1.table2[index2] <= num;
                rout <= 0;
            end
        end
    end

endmodule

FPGA-Assgn2/module31.v
//`include "module1.v"
//`include "module2.v"
`timescale 1ns/1ns

module mod31(input [31:0] num,
            input rin,
            output reg [31:0] num_o,
            output reg rout);

    mod1 m1();
    module2 m2();

    reg [4:0] index1;
    //reg [4:0] index2;

    always@(rin) begin
        #1;
        if (rin == 0)begin
            rout <= 0;
        end
        else begin
            for(integer i = 0; i <15; i+=1) begin
                if(m2.val[i] == num) begin
                    index1 <= m2.i1[i];
                    //index2 <= m2.i2[i];
                end
            end

            if(m1.table1_filled[index1] == 1) begin
                num_o <= m1.table1[index1];
                m1.table1[index1] <= num;
                rout <= 1;
            end
            else begin
                m1.table1_filled[index1] <= 1;
                m1.table1[index1] <= num;
                rout <= 0;
            end
        end
    end

endmodule

FPGA-Assgn2/topmodule.v
`include "module31.v"
`include "module32.v"
`include "module1.v"
`include "module2.v"
`timescale 1ns/1ns

module top(input [31:0] num);

    wire i;
    assign i = 1;
    wire [31:0] w1[19:0];
    wire w2[19:0];

    mod1 m1();
    module2 m2();

    mod31 m310 (.num(num), .num_o(w1[0]), .rin(i), .rout(w2[0]));
    mod32 m320 (.num(w1[0]), .num_o(w1[1]), .rin(w2[0]), .rout(w2[1]));
    
    mod31 m311 (.num(w1[1]), .num_o(w1[2]), .rin(w2[1]), .rout(w2[2]));
    mod32 m321 (.num(w1[2]), .num_o(w1[3]), .rin(w2[2]), .rout(w2[3]));

    mod31 m312 (.num(w1[3]), .num_o(w1[4]), .rin(w2[3]), .rout(w2[4]));
    mod32 m322 (.num(w1[4]), .num_o(w1[5]), .rin(w2[4]), .rout(w2[5]));
    
    mod31 m313 (.num(w1[5]), .num_o(w1[6]), .rin(w2[5]), .rout(w2[6]));
    mod32 m323 (.num(w1[6]), .num_o(w1[7]), .rin(w2[6]), .rout(w2[7]));

    mod31 m314 (.num(w1[7]), .num_o(w1[8]), .rin(w2[7]), .rout(w2[8]));
    mod32 m324 (.num(w1[8]), .num_o(w1[9]), .rin(w2[8]), .rout(w2[9]));
    
    mod31 m315 (.num(w1[9]), .num_o(w1[10]), .rin(w2[9]), .rout(w2[10]));
    mod32 m325 (.num(w1[10]), .num_o(w1[11]), .rin(w2[10]), .rout(w2[11]));
    
    mod31 m316 (.num(w1[11]), .num_o(w1[12]), .rin(w2[11]), .rout(w2[12]));
    mod32 m326 (.num(w1[12]), .num_o(w1[13]), .rin(w2[12]), .rout(w2[13]));
    
    mod31 m317 (.num(w1[13]), .num_o(w1[14]), .rin(w2[13]), .rout(w2[14]));
    mod32 m327 (.num(w1[14]), .num_o(w1[15]), .rin(w2[14]), .rout(w2[15]));
    
    mod31 m318 (.num(w1[15]), .num_o(w1[16]), .rin(w2[15]), .rout(w2[16]));
    mod32 m328 (.num(w1[16]), .num_o(w1[17]), .rin(w2[16]), .rout(w2[17]));
    
endmodule

FPGA-Assgn2/testbench_new.v
`include "topmodule.v"
`timescale 1ns/1ns
module tb;

reg [31:0] num;

top uut (.num(num));

initial begin
    $dumpfile("dump_new.vcd");
    $dumpvars(0,tb);
    
    num <=38;
    #100;
    for (integer i=0 ; i<20 ;i++) begin
        $display("%d : %d %d", i , uut.m1.table1_filled[i] , uut.m1.table1[i]);
    end;
    $display("\n");
    for (integer i=0 ; i<20 ;i++) begin
        $display("%d : %d %d", i , uut.m1.table2_filled[i] , uut.m1.table2[i]);
    end;
    $display("\n"); 
    #100;
    /*
    reset <= ~reset;
    num <=84;  i1 <=4;   i2 <=4;
    #100;
    for (integer i=0 ; i<20 ;i++) begin
        $display("%d : %d %d", i , uut.m1.table1_filled[i] , uut.m1.table1[i]);
    end;
    $display("\n");
    for (integer i=0 ; i<20 ;i++) begin
        $display("%d : %d %d", i , uut.m1.table2_filled[i] , uut.m1.table2[i]);
    end;
    $display("\n"); 
    reset <= ~reset;
    num <=76;  i1 <=16;   i2 <=16;
    #100;
    for (integer i=0 ; i<20 ;i++) begin
        $display("%d : %d %d", i , uut.m1.table1_filled[i] , uut.m1.table1[i]);
    end;
    $display("\n");
    for (integer i=0 ; i<20 ;i++) begin
        $display("%d : %d %d", i , uut.m1.table2_filled[i] , uut.m1.table2[i]);
    end;
    $display("\n"); 
    reset <= ~reset;
    num <=93;  i1 <=17;   i2 <=13;
    #100;
    for (integer i=0 ; i<20 ;i++) begin
        $display("%d : %d %d", i , uut.m1.table1_filled[i] , uut.m1.table1[i]);
    end;
    $display("\n");
    for (integer i=0 ; i<20 ;i++) begin
        $display("%d : %d %d", i , uut.m1.table2_filled[i] , uut.m1.table2[i]);
    end;
    $display("\n"); 
    reset <= ~reset;
    num <=8;  i1 <=12;   i2 <=4;
    #100;
    for (integer i=0 ; i<20 ;i++) begin
        $display("%d : %d %d", i , uut.m1.table1_filled[i] , uut.m1.table1[i]);
    end;
    $display("\n");
    for (integer i=0 ; i<20 ;i++) begin
        $display("%d : %d %d", i , uut.m1.table2_filled[i] , uut.m1.table2[i]);
    end;
    $display("\n"); 
    */
    $finish;
end
endmodule

FPGA-Assgn2/dump_new.vcd
$date
	Fri Jun 10 02:07:09 2022
$end
$version
	Icarus Verilog
$end
$timescale
	1ns
$end
$scope module tb $end
$var reg 32 ! num [31:0] $end
$scope module uut $end
$var wire 1 " i $end
$var wire 32 # num [31:0] $end
$scope module m1 $end
$var integer 32 $ i [31:0] $end
$upscope $end
$scope module m2 $end
$upscope $end
$scope module m310 $end
$var wire 32 % num [31:0] $end
$var wire 1 " rin $end
$var reg 5 & index1 [4:0] $end
$var reg 32 ' num_o [31:0] $end
$var reg 1 ( rout $end
$scope module m1 $end
$var integer 32 ) i [31:0] $end
$upscope $end
$scope module m2 $end
$upscope $end
$scope begin $ivl_for_loop0 $end
$var integer 32 * i [31:0] $end
$upscope $end
$upscope $end
$scope module m311 $end
$var wire 1 + rin $end
$var wire 32 , num [31:0] $end
$var reg 5 - index1 [4:0] $end
$var reg 32 . num_o [31:0] $end
$var reg 1 / rout $end
$scope module m1 $end
$var integer 32 0 i [31:0] $end
$upscope $end
$scope module m2 $end
$upscope $end
$scope begin $ivl_for_loop0 $end
$var integer 32 1 i [31:0] $end
$upscope $end
$upscope $end
$scope module m312 $end
$var wire 1 2 rin $end
$var wire 32 3 num [31:0] $end
$var reg 5 4 index1 [4:0] $end
$var reg 32 5 num_o [31:0] $end
$var reg 1 6 rout $end
$scope module m1 $end
$var integer 32 7 i [31:0] $end
$upscope $end
$scope module m2 $end
$upscope $end
$scope begin $ivl_for_loop0 $end
$var integer 32 8 i [31:0] $end
$upscope $end
$upscope $end
$scope module m313 $end
$var wire 1 9 rin $end
$var wire 32 : num [31:0] $end
$var reg 5 ; index1 [4:0] $end
$var reg 32 < num_o [31:0] $end
$var reg 1 = rout $end
$scope module m1 $end
$var integer 32 > i [31:0] $end
$upscope $end
$scope module m2 $end
$upscope $end
$scope begin $ivl_for_loop0 $end
$var integer 32 ? i [31:0] $end
$upscope $end
$upscope $end
$scope module m314 $end
$var wire 1 @ rin $end
$var wire 32 A num [31:0] $end
$var reg 5 B index1 [4:0] $end
$var reg 32 C num_o [31:0] $end
$var reg 1 D rout $end
$scope module m1 $end
$var integer 32 E i [31:0] $end
$upscope $end
$scope module m2 $end
$upscope $end
$scope begin $ivl_for_loop0 $end
$var integer 32 F i [31:0] $end
$upscope $end
$upscope $end
$scope module m315 $end
$var wire 1 G rin $end
$var wire 32 H num [31:0] $end
$var reg 5 I index1 [4:0] $end
$var reg 32 J num_o [31:0] $end
$var reg 1 K rout $end
$scope module m1 $end
$var integer 32 L i [31:0] $end
$upscope $end
$scope module m2 $end
$upscope $end
$scope begin $ivl_for_loop0 $end
$var integer 32 M i [31:0] $end
$upscope $end
$upscope $end
$scope module m316 $end
$var wire 1 N rin $end
$var wire 32 O num [31:0] $end
$var reg 5 P index1 [4:0] $end
$var reg 32 Q num_o [31:0] $end
$var reg 1 R rout $end
$scope module m1 $end
$var integer 32 S i [31:0] $end
$upscope $end
$scope module m2 $end
$upscope $end
$scope begin $ivl_for_loop0 $end
$var integer 32 T i [31:0] $end
$upscope $end
$upscope $end
$scope module m317 $end
$var wire 1 U rin $end
$var wire 32 V num [31:0] $end
$var reg 5 W index1 [4:0] $end
$var reg 32 X num_o [31:0] $end
$var reg 1 Y rout $end
$scope module m1 $end
$var integer 32 Z i [31:0] $end
$upscope $end
$scope module m2 $end
$upscope $end
$scope begin $ivl_for_loop0 $end
$var integer 32 [ i [31:0] $end
$upscope $end
$upscope $end
$scope module m318 $end
$var wire 1 \ rin $end
$var wire 32 ] num [31:0] $end
$var reg 5 ^ index1 [4:0] $end
$var reg 32 _ num_o [31:0] $end
$var reg 1 ` rout $end
$scope module m1 $end
$var integer 32 a i [31:0] $end
$upscope $end
$scope module m2 $end
$upscope $end
$scope begin $ivl_for_loop0 $end
$var integer 32 b i [31:0] $end
$upscope $end
$upscope $end
$scope module m320 $end
$var wire 32 c num [31:0] $end
$var wire 1 ( rin $end
$var reg 5 d index2 [4:0] $end
$var reg 32 e num_o [31:0] $end
$var reg 1 + rout $end
$scope module m1 $end
$var integer 32 f i [31:0] $end
$upscope $end
$scope module m2 $end
$upscope $end
$scope begin $ivl_for_loop1 $end
$var integer 32 g i [31:0] $end
$upscope $end
$upscope $end
$scope module m321 $end
$var wire 32 h num [31:0] $end
$var wire 1 / rin $end
$var reg 5 i index2 [4:0] $end
$var reg 32 j num_o [31:0] $end
$var reg 1 2 rout $end
$scope module m1 $end
$var integer 32 k i [31:0] $end
$upscope $end
$scope module m2 $end
$upscope $end
$scope begin $ivl_for_loop1 $end
$var integer 32 l i [31:0] $end
$upscope $end
$upscope $end
$scope module m322 $end
$var wire 32 m num [31:0] $end
$var wire 1 6 rin $end
$var reg 5 n index2 [4:0] $end
$var reg 32 o num_o [31:0] $end
$var reg 1 9 rout $end
$scope module m1 $end
$var integer 32 p i [31:0] $end
$upscope $end
$scope module m2 $end
$upscope $end
$scope begin $ivl_for_loop1 $end
$var integer 32 q i [31:0] $end
$upscope $end
$upscope $end
$scope module m323 $end
$var wire 32 r num [31:0] $end
$var wire 1 = rin $end
$var reg 5 s index2 [4:0] $end
$var reg 32 t num_o [31:0] $end
$var reg 1 @ rout $end
$scope module m1 $end
$var integer 32 u i [31:0] $end
$upscope $end
$scope module m2 $end
$upscope $end
$scope begin $ivl_for_loop1 $end
$var integer 32 v i [31:0] $end
$upscope $end
$upscope $end
$scope module m324 $end
$var wire 32 w num [31:0] $end
$var wire 1 D rin $end
$var reg 5 x index2 [4:0] $end
$var reg 32 y num_o [31:0] $end
$var reg 1 G rout $end
$scope module m1 $end
$var integer 32 z i [31:0] $end
$upscope $end
$scope module m2 $end
$upscope $end
$scope begin $ivl_for_loop1 $end
$var integer 32 { i [31:0] $end
$upscope $end
$upscope $end
$scope module m325 $end
$var wire 32 | num [31:0] $end
$var wire 1 K rin $end
$var reg 5 } index2 [4:0] $end
$var reg 32 ~ num_o [31:0] $end
$var reg 1 N rout $end
$scope module m1 $end
$var integer 32 !" i [31:0] $end
$upscope $end
$scope module m2 $end
$upscope $end
$scope begin $ivl_for_loop1 $end
$var integer 32 "" i [31:0] $end
$upscope $end
$upscope $end
$scope module m326 $end
$var wire 32 #" num [31:0] $end
$var wire 1 R rin $end
$var reg 5 $" index2 [4:0] $end
$var reg 32 %" num_o [31:0] $end
$var reg 1 U rout $end
$scope module m1 $end
$var integer 32 &" i [31:0] $end
$upscope $end
$scope module m2 $end
$upscope $end
$scope begin $ivl_for_loop1 $end
$var integer 32 '" i [31:0] $end
$upscope $end
$upscope $end
$scope module m327 $end
$var wire 32 (" num [31:0] $end
$var wire 1 Y rin $end
$var reg 5 )" index2 [4:0] $end
$var reg 32 *" num_o [31:0] $end
$var reg 1 \ rout $end
$scope module m1 $end
$var integer 32 +" i [31:0] $end
$upscope $end
$scope module m2 $end
$upscope $end
$scope begin $ivl_for_loop1 $end
$var integer 32 ," i [31:0] $end
$upscope $end
$upscope $end
$scope module m328 $end
$var wire 32 -" num [31:0] $end
$var wire 1 ` rin $end
$var reg 5 ." index2 [4:0] $end
$var reg 32 /" num_o [31:0] $end
$var reg 1 0" rout $end
$scope module m1 $end
$var integer 32 1" i [31:0] $end
$upscope $end
$scope module m2 $end
$upscope $end
$scope begin $ivl_for_loop1 $end
$var integer 32 2" i [31:0] $end
$upscope $end
$upscope $end
$upscope $end
$scope begin $ivl_for_loop2 $end
$var integer 32 3" i [31:0] $end
$upscope $end
$scope begin $ivl_for_loop3 $end
$var integer 32 4" i [31:0] $end
$upscope $end
$upscope $end
$enddefinitions $end
#0
$dumpvars
bx 4"
bx 3"
bx 2"
b10100 1"
x0"
bx /"
bx ."
bx -"
bx ,"
b10100 +"
bx *"
bx )"
bx ("
bx '"
b10100 &"
bx %"
bx $"
bx #"
bx ""
b10100 !"
bx ~
bx }
bx |
bx {
b10100 z
bx y
bx x
bx w
bx v
b10100 u
bx t
bx s
bx r
bx q
b10100 p
bx o
bx n
bx m
bx l
b10100 k
bx j
bx i
bx h
bx g
b10100 f
bx e
bx d
bx c
bx b
b10100 a
x`
bx _
bx ^
bx ]
x\
bx [
b10100 Z
xY
bx X
bx W
bx V
xU
bx T
b10100 S
xR
bx Q
bx P
bx O
xN
bx M
b10100 L
xK
bx J
bx I
bx H
xG
bx F
b10100 E
xD
bx C
bx B
bx A
x@
bx ?
b10100 >
x=
bx <
bx ;
bx :
x9
bx 8
b10100 7
x6
bx 5
bx 4
bx 3
x2
bx 1
b10100 0
x/
bx .
bx -
bx ,
x+
bx *
b10100 )
x(
bx '
bx &
b100110 %
b10100 $
b100110 #
1"
b100110 !
$end
#1
0(
b1111 *
#2
0+
#3
0/
#4
02
#5
06
#6
09
#7
0=
#8
0@
#9
0D
#10
0G
#11
0K
#12
0N
#13
0R
#14
0U
#15
0Y
#16
0\
#17
0`
#18
00"
#100
b10100 4"
b10100 3"
